main.py
mvtcli-0.1.1.dist-info/METADATA
mvtcli-0.1.1.dist-info/WHEEL
mvtcli-0.1.1.dist-info/entry_points.txt
mvtcli-0.1.1.dist-info/top_level.txt
mvtcli-0.1.1.dist-info/RECORD
