Metadata-Version: 2.4
Name: mvtcli
Version: 0.1.1
Summary: Add your description here
Requires-Python: >=3.08
Requires-Dist: click>=8.1.8
Requires-Dist: mapbox-vector-tile>=2.0.1
Requires-Dist: mercantile>=1.2.1
Requires-Dist: shapely>=2.0.7
